binomcikit/__init__.py
binomcikit/a_101_n_confidence_base.py
binomcikit/a_102_n_confidence_base_graph.py
binomcikit/a_103_n_x_confidence_intervals_base.py
binomcikit/a_104_n_x_confidence_intervals_base_graph.py
binomcikit/a_111_n_adj_confidence_intervals.py
binomcikit/a_112_n_adj_confidence_intervals_graph.py
binomcikit/a_113_n_x_adj_confidence_intervals.py
binomcikit/a_121_cc_n_confidence_intervals.py
binomcikit/a_122_cc_n_confidence_intervals_graph.py
binomcikit/a_123_cc_n_x_confidence_intervals.py
binomcikit-0.0.5.dist-info/LICENSE.txt
binomcikit-0.0.5.dist-info/METADATA
binomcikit-0.0.5.dist-info/WHEEL
binomcikit-0.0.5.dist-info/top_level.txt
binomcikit-0.0.5.dist-info/RECORD
