Metadata-Version: 2.2
Name: binomcikit
Version: 0.0.5
Summary: Used to calculate Confidence Intervals
Author-email: "Vyasa R Rajeswaran, Pranava BA, Justindhas Y" <pranavabaascaran@gmail.com>
License: GPL-3.0
Project-URL: Homepage, https://github.com/pranava-ba/binomcikit
Project-URL: Issues, https://github.com/pranava-ba/binomcikit/issues
Classifier: Programming Language :: Python :: 3
Classifier: License :: OSI Approved :: GNU General Public License v3 (GPLv3)
Classifier: Operating System :: OS Independent
Requires-Python: >=3.0
License-File: LICENSE.txt
Requires-Dist: numpy
Requires-Dist: pandas
Requires-Dist: scipy
Requires-Dist: plotnine
